dictdiffer/__init__.py
dictdiffer/_compat.py
dictdiffer/conflict.py
dictdiffer/merge.py
dictdiffer/resolve.py
dictdiffer/unify.py
dictdiffer/utils.py
dictdiffer/version.py
inspire_dictdiffer-0.8.1.dist-info/LICENSE
inspire_dictdiffer-0.8.1.dist-info/METADATA
inspire_dictdiffer-0.8.1.dist-info/WHEEL
inspire_dictdiffer-0.8.1.dist-info/top_level.txt
inspire_dictdiffer-0.8.1.dist-info/RECORD
